miniorm
