Metadata-Version: 1.0
Name: miniorm
Version: 1.8.1
Summary: mini mysql db orm :: miniorm :: with connection pool
Home-page: UNKNOWN
Author: inwn
Author-email: ininwn@gmail.com
License: MIT
Keywords: mini mysql db orm :: miniorm
Platform: UNKNOWN
